abtoolkit/__init__.py
abtoolkit/utils.py
abtoolkit/continuous/__init__.py
abtoolkit/continuous/simulation.py
abtoolkit/continuous/stattests.py
abtoolkit/continuous/utils.py
abtoolkit/discrete/__init__.py
abtoolkit/discrete/simulation.py
abtoolkit/discrete/stattests.py
abtoolkit/discrete/utils.py
examples/check_clt.py
examples/continuous_var_analysis.py
examples/discrete_var_analysis.py
static/discrete-output-plot.png
static/discrete-p-value-plot.png
static/output-plot.png
static/p-value-plot.png
tests/__init__.py
tests/test_continuous_simulation.py
tests/test_continuous_stattests.py
tests/test_continuous_utils.py
tests/test_discrete_simulation.py
tests/test_discrete_stattests.py
tests/test_discrete_utils.py
tests/test_utils.py
venv/bin/activate_this.py
venv/bin/rst2html.py
venv/bin/rst2html4.py
venv/bin/rst2html5.py
venv/bin/rst2latex.py
venv/bin/rst2man.py
venv/bin/rst2odt.py
venv/bin/rst2odt_prepstyles.py
venv/bin/rst2pseudoxml.py
venv/bin/rst2s5.py
venv/bin/rst2xetex.py
venv/bin/rst2xml.py
venv/bin/rstpep2html.py
abtoolkit-2.0.0.dist-info/LICENSE
abtoolkit-2.0.0.dist-info/METADATA
abtoolkit-2.0.0.dist-info/WHEEL
abtoolkit-2.0.0.dist-info/top_level.txt
abtoolkit-2.0.0.dist-info/RECORD
