Metadata-Version: 2.1
Name: abtoolkit
Version: 2.0.0
Summary: Package with tools for AB testing
Author-email: Nikita Altukhov <altuxov.nikita@gmail.com>
Project-URL: Homepage, https://github.com/nikitosl/abtoolkit
Project-URL: Issues, https://github.com/nikitosl/abtoolkit/issues
Keywords: ab_test,cuped,did,ttest
Classifier: Programming Language :: Python :: 3
Classifier: License :: OSI Approved :: MIT License
Classifier: Operating System :: OS Independent
Requires-Python: >=3.8
License-File: LICENSE
Requires-Dist: pandas>=2.2.1
Requires-Dist: numpy>=1.26.4
Requires-Dist: statsmodels>=0.14.1
Requires-Dist: scipy>=1.12.0
Requires-Dist: linearmodels>=5.4
Requires-Dist: tqdm>=4.66.2
